osha.oira-12.5.3-py3.13-nspkg.pth
osha/oira/__init__.py
osha/oira/configure.zcml
osha/oira/initdb.py
osha/oira/interfaces.py
osha/oira/manual_translations.py
osha/oira/overrides.zcml
osha/oira/scripts.py
osha/oira/sql_scripts.py
osha/oira/testing.py
osha/oira/vocabularies.py
osha/oira/client/__init__.py
osha/oira/client/client.py
osha/oira/client/configure.zcml
osha/oira/client/indexers.py
osha/oira/client/interfaces.py
osha/oira/client/model.py
osha/oira/client/subscribers.py
osha/oira/client/browser/__init__.py
osha/oira/client/browser/certificate.py
osha/oira/client/browser/client.py
osha/oira/client/browser/conditions.py
osha/oira/client/browser/configure.zcml
osha/oira/client/browser/dashboard_banner.py
osha/oira/client/browser/fr.py
osha/oira/client/browser/login.py
osha/oira/client/browser/module.py
osha/oira/client/browser/report.py
osha/oira/client/browser/session.py
osha/oira/client/browser/settings.py
osha/oira/client/browser/webhelpers.py
osha/oira/client/browser/templates/appendix.pt
osha/oira/client/browser/templates/certificate-print.pt
osha/oira/client/browser/templates/certificate.pt
osha/oira/client/browser/templates/certificate_fr_specific.pt
osha/oira/client/browser/templates/certificate_inner.pt
osha/oira/client/browser/templates/dashboard-banner.pt
osha/oira/client/browser/templates/disclaimer.pt
osha/oira/client/browser/templates/module_actionplan.pt
osha/oira/client/browser/templates/module_identification.pt
osha/oira/client/browser/templates/preferences.pt
osha/oira/client/browser/templates/privacy_policy.pt
osha/oira/client/browser/templates/public-certificate.pt
osha/oira/client/browser/templates/status-tooltip.pt
osha/oira/client/browser/templates/status.pt
osha/oira/client/browser/templates/unsubscribe.pt
osha/oira/client/resources/__init__.py
osha/oira/client/resources/andrea-piacquadio-copier.jpg
osha/oira/client/resources/certificate-8.svg
osha/oira/client/resources/creative_commons.png
osha/oira/client/resources/footer_logo.png
osha_oira-12.5.3.dist-info/METADATA
osha_oira-12.5.3.dist-info/WHEEL
osha_oira-12.5.3.dist-info/entry_points.txt
osha_oira-12.5.3.dist-info/namespace_packages.txt
osha_oira-12.5.3.dist-info/top_level.txt
osha_oira-12.5.3.dist-info/RECORD
