Metadata-Version: 2.4
Name: osha.oira
Version: 12.5.3
Summary: Euphorie customisations for OSHA-OiRA site.
Home-page: http://www.oiraproject.eu/
Author: syslab.com
Author-email: info@syslab.com
License: GPL
Keywords: euphorie osha oira
Classifier: Development Status :: 5 - Production/Stable
Classifier: Environment :: Web Environment
Classifier: Framework :: Plone
Classifier: Framework :: Plone :: 6.1
Classifier: License :: OSI Approved :: GNU General Public License (GPL)
Classifier: Programming Language :: Python :: 3
Classifier: Programming Language :: Python :: 3.11
Classifier: Programming Language :: Python :: 3.12
Classifier: Programming Language :: Python :: 3.13
Classifier: Topic :: Internet :: WWW/HTTP
Classifier: Topic :: Software Development :: Libraries :: Python Modules
Requires-Python: >=3.11
Requires-Dist: Euphorie>=14.0.0
Requires-Dist: ftw.upgrade
Requires-Dist: mobile.sniffer
Requires-Dist: NuPlone>=4.0.1
Requires-Dist: pas.plugins.ldap
Requires-Dist: Pillow
Requires-Dist: plone.api
Requires-Dist: plone.autoform
Requires-Dist: plone.formwidget.recaptcha
Requires-Dist: plone.restapi
Requires-Dist: plone.tiles
Requires-Dist: Products.MemcachedManager
Requires-Dist: Products.statusmessages
Requires-Dist: requests
Requires-Dist: setuptools
Requires-Dist: slc.zopescript
Requires-Dist: zope.app.publication
Requires-Dist: zope.publisher
Provides-Extra: tests
Requires-Dist: Euphorie[tests]; extra == "tests"
Requires-Dist: node.ext.ldap; extra == "tests"
Requires-Dist: pas.plugins.ldap; extra == "tests"
Requires-Dist: plone.app.robotframework[debug]; extra == "tests"
Requires-Dist: plone.app.testing; extra == "tests"
Dynamic: author
Dynamic: author-email
Dynamic: classifier
Dynamic: description
Dynamic: home-page
Dynamic: keywords
Dynamic: license
Dynamic: provides-extra
Dynamic: requires-dist
Dynamic: requires-python
Dynamic: summary
